<?xml version="1.0" encoding="utf-8" ?>
<dwsync>
<file name="fieldbg.gif" server="C:/Servers/Apache Software Foundation/Apache2.2/htdocs/PruebaImagine" local="129592082820000000" remote="129592082820000000" />
<file name="wflogo.png" server="C:/Servers/Apache Software Foundation/Apache2.2/htdocs/PruebaImagine" local="129592082820000000" remote="129592082820000000" />
<file name="iepngfix.htc" server="C:/Servers/Apache Software Foundation/Apache2.2/htdocs/PruebaImagine" local="129592082820000000" remote="129592082820000000" />
<file name="bottom.png" server="C:/Servers/Apache Software Foundation/Apache2.2/htdocs/PruebaImagine/" local="129592082820000000" remote="129592082820000000" />
<file name="calendar.png" server="C:/Servers/Apache Software Foundation/Apache2.2/htdocs/PruebaImagine/" local="129592082820000000" remote="129592082820000000" />
<file name="powerlogo.png" server="C:/Servers/Apache Software Foundation/Apache2.2/htdocs/PruebaImagine/" local="129592082820000000" remote="129592082820000000" />
<file name="wflogo_1.png" server="C:/Servers/Apache Software Foundation/Apache2.2/htdocs/PruebaImagine/" local="129592082820000000" remote="129592082820000000" />
<file name="fieldbg.gif" server="C:/Servers/Apache Software Foundation/Apache2.2/htdocs/PruebaImagine/" local="129592082820000000" remote="129592082820000000" />
<file name="wflogo.png" server="C:/Servers/Apache Software Foundation/Apache2.2/htdocs/PruebaImagine/" local="129592082820000000" remote="129592082820000000" />
<file name="iepngfix.htc" server="C:/Servers/Apache Software Foundation/Apache2.2/htdocs/PruebaImagine/" local="129592082820000000" remote="129592082820000000" />
</dwsync>